spark_auto_mapper_fhir/__init__.py
spark_auto_mapper_fhir/classproperty.py
spark_auto_mapper_fhir/py.typed
spark_auto_mapper_fhir/backbone_elements/Immunization_reaction_backbone_element.py
spark_auto_mapper_fhir/backbone_elements/__init__.py
spark_auto_mapper_fhir/backbone_elements/accident_backbone_element.py
spark_auto_mapper_fhir/backbone_elements/action_backbone_element.py
spark_auto_mapper_fhir/backbone_elements/action_relationship_type.py
spark_auto_mapper_fhir/backbone_elements/adjudication_backbone_element.py
spark_auto_mapper_fhir/backbone_elements/appointment_participant_backbone_element.py
spark_auto_mapper_fhir/backbone_elements/benefit_backbone_element.py
spark_auto_mapper_fhir/backbone_elements/benefit_limit_backbone_element.py
spark_auto_mapper_fhir/backbone_elements/care_team_backbone_element.py
spark_auto_mapper_fhir/backbone_elements/care_team_participant_backbone_element.py
spark_auto_mapper_fhir/backbone_elements/condition_backbone_element.py
spark_auto_mapper_fhir/backbone_elements/condition_evidence_backbone_element.py
spark_auto_mapper_fhir/backbone_elements/condition_stage_backbone_element.py
spark_auto_mapper_fhir/backbone_elements/contact_backbone_element.py
spark_auto_mapper_fhir/backbone_elements/cost_to_beneficiary_backbone_element.py
spark_auto_mapper_fhir/backbone_elements/coverage_backbone_element.py
spark_auto_mapper_fhir/backbone_elements/coverage_classification_backbone_element.py
spark_auto_mapper_fhir/backbone_elements/coverage_financial_exception_backbone_element.py
spark_auto_mapper_fhir/backbone_elements/diagnosis_backbone_element.py
spark_auto_mapper_fhir/backbone_elements/diagnostic_report_media_backbone_element.py
spark_auto_mapper_fhir/backbone_elements/dispense_request_backbone_element.py
spark_auto_mapper_fhir/backbone_elements/eligibility_backbone_element.py
spark_auto_mapper_fhir/backbone_elements/encounter_class_history_backbone_element.py
sparkautomapper.fhir-0.2.21.dist-info/LICENSE
sparkautomapper.fhir-0.2.21.dist-info/METADATA
sparkautomapper.fhir-0.2.21.dist-info/WHEEL
sparkautomapper.fhir-0.2.21.dist-info/top_level.txt
sparkautomapper.fhir-0.2.21.dist-info/RECORD
