Metadata-Version: 2.1
Name: sparkautomapper.fhir
Version: 0.2.21
Summary: FHIR extensions for SparkAutoMapper
Home-page: https://github.com/imranq2/SparkAutoMapper.FHIR
Author: Imran Qureshi
Author-email: imranq2@hotmail.com
License: UNKNOWN
Platform: UNKNOWN
Classifier: Development Status :: 4 - Beta
Classifier: Programming Language :: Python :: 3
Classifier: License :: OSI Approved :: Apache Software License
Classifier: Operating System :: OS Independent
Requires-Python: >=3.6,<4
